KuFlow/__init__.py
KuFlow/keywords.py
kuflow_robotframework-3.2.1.dist-info/METADATA
kuflow_robotframework-3.2.1.dist-info/WHEEL
kuflow_robotframework-3.2.1.dist-info/RECORD
