Metadata-Version: 2.3
Name: kuflow-robotframework
Version: 3.2.1
Summary: KuFlow library for Robot Framework
License: MIT
Author: KuFlow S.L.
Author-email: kuflow@kuflow.com
Requires-Python: >=3.9,<4.0
Classifier: License :: OSI Approved :: MIT License
Classifier: Programming Language :: Python :: 3
Classifier: Programming Language :: Python :: 3.9
Classifier: Programming Language :: Python :: 3.10
Classifier: Programming Language :: Python :: 3.11
Classifier: Programming Language :: Python :: 3.12
Classifier: Programming Language :: Python :: 3.13
Requires-Dist: kuflow-rest (>=3.2.1,<4.0.0)
Requires-Dist: python-magic (>=0.4.27,<0.5.0) ; sys_platform != "win32"
Requires-Dist: python-magic-bin (>=0.4.14,<0.5.0) ; sys_platform == "win32"
Requires-Dist: robotframework (>5.0.0)
Project-URL: Documentation, https://docs.kuflow.com/
Project-URL: Homepage, https://kuflow.com/
Project-URL: Repository, https://github.com/kuflow/kuflow-sdk-python
